tfresurrect/__init__.py
tfresurrect/cli.py
tfresurrect/cli.py~
tfresurrect-0.1.0.dist-info/entry_points.txt
tfresurrect-0.1.0.dist-info/WHEEL
tfresurrect-0.1.0.dist-info/METADATA
tfresurrect-0.1.0.dist-info/RECORD
