Metadata-Version: 2.1
Name: tfresurrect
Version: 0.1.0
Summary: resurrect terraform state
License: Apache 2.0
Author: Kapil Thangavelu
Author-email: hello@stacklet.io
Requires-Python: >=3.8,<4.0
Classifier: License :: Other/Proprietary License
Classifier: Programming Language :: Python :: 3
Classifier: Programming Language :: Python :: 3.8
Classifier: Programming Language :: Python :: 3.9
Requires-Dist: c7n (>=0.9.11,<0.10.0)
Requires-Dist: python-hcl2 (>=2.0.3,<3.0.0)
